<?xml version="1.0" encoding="UTF-8"?>
<container xmlns="http://symfony.com/schema/dic/services" xmlns:xsi="http://www.w3.org/2001/XMLSchema-instance" xsi:schemaLocation="http://symfony.com/schema/dic/services http://symfony.com/schema/dic/services/services-1.0.xsd">
    <services>
        <!-- NEXT_MAJOR: remove the "class" and "public" attributes -->
        <service id="Sonata\UserBundle\Action\RequestAction" class="Sonata\UserBundle\Action\RequestAction" public="true">
            <argument type="service" id="twig"/>
            <argument type="service" id="router"/>
            <argument type="service" id="security.authorization_checker"/>
            <argument type="service" id="sonata.admin.pool"/>
            <argument type="service" id="sonata.admin.global_template_registry"/>
        </service>
        <service id="Sonata\UserBundle\Action\SendEmailAction" class="Sonata\UserBundle\Action\SendEmailAction" public="true">
            <argument type="service" id="twig"/>
            <argument type="service" id="router"/>
            <argument type="service" id="sonata.admin.pool"/>
            <argument type="service" id="sonata.admin.global_template_registry"/>
            <argument type="service" id="fos_user.user_manager"/>
            <argument type="service" id="sonata.user.mailer"/>
            <argument type="service" id="fos_user.util.token_generator"/>
            <argument>%fos_user.resetting.retry_ttl%</argument>
        </service>
        <service id="Sonata\UserBundle\Action\CheckEmailAction" class="Sonata\UserBundle\Action\CheckEmailAction" public="true">
            <argument type="service" id="twig"/>
            <argument type="service" id="router"/>
            <argument type="service" id="sonata.admin.pool"/>
            <argument type="service" id="sonata.admin.global_template_registry"/>
            <argument>%fos_user.resetting.retry_ttl%</argument>
        </service>
        <service id="Sonata\UserBundle\Action\ResetAction" class="Sonata\UserBundle\Action\ResetAction" public="true">
            <argument type="service" id="twig"/>
            <argument type="service" id="router"/>
            <argument type="service" id="security.authorization_checker"/>
            <argument type="service" id="sonata.admin.pool"/>
            <argument type="service" id="sonata.admin.global_template_registry"/>
            <argument type="service" id="fos_user.resetting.form.factory"/>
            <argument type="service" id="fos_user.user_manager"/>
            <argument type="service" id="fos_user.security.login_manager"/>
            <argument type="service" id="translator"/>
            <argument type="service" id="session"/>
            <argument>%fos_user.resetting.retry_ttl%</argument>
            <argument>%fos_user.firewall_name%</argument>
            <call method="setLogger">
                <argument type="service" id="logger" on-invalid="ignore"/>
            </call>
        </service>
        <service id="Sonata\UserBundle\Action\LoginAction" class="Sonata\UserBundle\Action\LoginAction" public="true">
            <argument type="service" id="twig"/>
            <argument type="service" id="router"/>
            <argument type="service" id="security.authorization_checker"/>
            <argument type="service" id="sonata.admin.pool"/>
            <argument type="service" id="sonata.admin.global_template_registry"/>
            <argument type="service" id="security.token_storage"/>
            <argument type="service" id="session"/>
            <call method="setCsrfTokenManager">
                <argument type="service" id="security.csrf.token_manager" on-invalid="ignore"/>
            </call>
        </service>
        <service id="Sonata\UserBundle\Action\CheckLoginAction" class="Sonata\UserBundle\Action\CheckLoginAction" public="true"/>
        <service id="Sonata\UserBundle\Action\LogoutAction" class="Sonata\UserBundle\Action\LogoutAction" public="true"/>
    </services>
</container>
